beaver/__init__.py
beaver/cli.py
beaver/computation.py
beaver/datasets.py
beaver/envelope.py
beaver/lib_support.py
beaver/live_mixin.py
beaver/live_var.py
beaver/mappings.py
beaver/policy.py
beaver/remote_data.py
beaver/remote_vars.py
beaver/runtime.py
beaver/session.py
beaver/settings.py
beaver/syft_url.py
beaver/syftbox_backend.py
beaver/twin.py
beaver/twin_func.py
beaver/twin_result.py
beaver/workspace.py
beaver/sample_data/__init__.py
biovault_beaver-0.1.45.dist-info/METADATA
biovault_beaver-0.1.45.dist-info/WHEEL
biovault_beaver-0.1.45.dist-info/entry_points.txt
biovault_beaver-0.1.45.dist-info/RECORD
