Metadata-Version: 2.4
Name: biovault-beaver
Version: 0.1.45
Summary: A library for data visitation and eager execution of remote bioinformatics workflows.
Author: Madhava Jay <madhava@openmined.org>
License: Apache-2.0
Classifier: Development Status :: 3 - Alpha
Classifier: Intended Audience :: Science/Research
Classifier: License :: OSI Approved :: Apache Software License
Classifier: Programming Language :: Python :: 3
Classifier: Programming Language :: Python :: 3.9
Classifier: Programming Language :: Python :: 3.10
Classifier: Programming Language :: Python :: 3.11
Classifier: Programming Language :: Python :: 3.12
Classifier: Programming Language :: Python :: 3.13
Classifier: Topic :: Scientific/Engineering :: Bio-Informatics
Requires-Python: <3.15,>=3.9
Requires-Dist: numpy
Requires-Dist: pyfory==0.13.2
Requires-Dist: pyyaml>=6.0
Requires-Dist: restrictedpython>=8.0
Requires-Dist: syftbox-sdk>=0.1.10
Requires-Dist: zstandard>=0.20.0
Provides-Extra: dev
Requires-Dist: mypy>=1.11.0; extra == 'dev'
Requires-Dist: pytest-cov>=4.1.0; extra == 'dev'
Requires-Dist: pytest>=8.0.0; extra == 'dev'
Requires-Dist: ruff>=0.8.0; extra == 'dev'
Requires-Dist: vulture>=2.11; extra == 'dev'
Provides-Extra: format
Requires-Dist: pyarrow; extra == 'format'
Provides-Extra: lib-support
Requires-Dist: anndata; extra == 'lib-support'
Requires-Dist: matplotlib; extra == 'lib-support'
Requires-Dist: numpy; extra == 'lib-support'
Requires-Dist: pandas>=1.3.0; extra == 'lib-support'
Requires-Dist: pillow; extra == 'lib-support'
Requires-Dist: pyarrow<22.0.0,>=12.0.0; extra == 'lib-support'
Requires-Dist: safetensors; extra == 'lib-support'
Requires-Dist: torch; extra == 'lib-support'
